myrabbit/__init__.py
myrabbit/commands/__init__.py
myrabbit/commands/command_bus.py
myrabbit/commands/command_bus_adapter.py
myrabbit/commands/command_outcome.py
myrabbit/commands/command_with_message.py
myrabbit/commands/reply_headers.py
myrabbit/contrib/__init__.py
myrabbit/contrib/opentelemetry/__init__.py
myrabbit/contrib/opentelemetry/instrumentor.py
myrabbit/core/__init__.py
myrabbit/core/consumer/__init__.py
myrabbit/core/consumer/callbacks.py
myrabbit/core/consumer/channel.py
myrabbit/core/consumer/consumer.py
myrabbit/core/consumer/handle_message_strategy.py
myrabbit/core/consumer/listener.py
myrabbit/core/consumer/message_handler.py
myrabbit/core/consumer/pika_message.py
myrabbit/core/consumer/reconnecting_consumer.py
myrabbit/core/consumer/reply.py
myrabbit/core/converter/__init__.py
myrabbit/core/converter/converter.py
myrabbit/core/converter/dataclass.py
myrabbit/core/converter/pydantic.py
myrabbit/core/publisher/__init__.py
myrabbit/core/publisher/publisher.py
myrabbit/core/publisher/reconnecting_publisher.py
myrabbit/core/publisher/rpc.py
myrabbit/core/serializer/__init__.py
myrabbit/core/serializer/json_serializer.py
myrabbit/core/serializer/serializer.py
myrabbit/events/__init__.py
myrabbit/events/event_bus.py
myrabbit/events/event_bus_adapter.py
myrabbit/events/event_with_message.py
myrabbit/events/listen_event_strategy/__init__.py
myrabbit/events/listen_event_strategy/base.py
myrabbit/events/listen_event_strategy/broadcast.py
myrabbit/events/listen_event_strategy/service_pool.py
myrabbit/events/listen_event_strategy/singleton.py
myrabbit/service/__init__.py
myrabbit/service/doc.py
myrabbit/service/runner.py
myrabbit/service/service.py
myrabbit/service/service_builder.py
myrabbit/utils/__init__.py
myrabbit/utils/functions.py
myrabbit-0.1.16.dist-info/WHEEL
myrabbit-0.1.16.dist-info/METADATA
myrabbit-0.1.16.dist-info/RECORD
